streamlit_funplayer/__init__.py
streamlit_funplayer/frontend/.env
streamlit_funplayer/frontend/.prettierrc
streamlit_funplayer/frontend/index.html
streamlit_funplayer/frontend/package-lock.json
streamlit_funplayer/frontend/package.json
streamlit_funplayer/frontend/test-webcomponent.html
streamlit_funplayer/frontend/tsconfig.json
streamlit_funplayer/frontend/vite.config.embed.ts
streamlit_funplayer/frontend/vite.config.ts
streamlit_funplayer/frontend/build/bootstrap.min.css
streamlit_funplayer/frontend/build/index.html
streamlit_funplayer/frontend/build/assets/main-CoN8iFNy.css
streamlit_funplayer/frontend/build/assets/main-DdMWAwpf.js
streamlit_funplayer/frontend/build/assets/videojs-playlist.es-BvE0lihi.js
streamlit_funplayer/frontend/build/assets/videojs-vr-CHzw7_q-.css
streamlit_funplayer/frontend/build/assets/videojs-vr-biliRIn8.js
streamlit_funplayer/frontend/build-embed/bootstrap.min.css
streamlit_funplayer/frontend/build-embed/funplayer-embed.js
streamlit_funplayer/frontend/public/bootstrap.min.css
streamlit_funplayer/frontend/src/Actuator.js
streamlit_funplayer/frontend/src/ActuatorSettingsComponent.jsx
streamlit_funplayer/frontend/src/ButtPlugManager.js
streamlit_funplayer/frontend/src/ButtPlugSettingsComponent.jsx
streamlit_funplayer/frontend/src/Channel.js
streamlit_funplayer/frontend/src/ChannelSettingsComponent.jsx
streamlit_funplayer/frontend/src/FeatherIcon.jsx
streamlit_funplayer/frontend/src/FunPlayer.jsx
streamlit_funplayer/frontend/src/FunPlayerCore.js
streamlit_funplayer/frontend/src/FunPlayerEvents.js
streamlit_funplayer/frontend/src/FunPlayerWebComponent.js
streamlit_funplayer/frontend/src/FunscriptManager.js
streamlit_funplayer/frontend/src/HapticSettingsComponent.jsx
streamlit_funplayer/frontend/src/HapticVisualizerComponent.jsx
streamlit_funplayer/frontend/src/LoggingComponent.jsx
streamlit_funplayer/frontend/src/LoggingManager.js
streamlit_funplayer/frontend/src/Logo.jsx
streamlit_funplayer/frontend/src/MediaPlayer.jsx
streamlit_funplayer-0.1.29.dist-info/licenses/LICENSE
streamlit_funplayer-0.1.29.dist-info/METADATA
streamlit_funplayer-0.1.29.dist-info/WHEEL
streamlit_funplayer-0.1.29.dist-info/top_level.txt
streamlit_funplayer-0.1.29.dist-info/RECORD
