Metadata-Version: 2.4
Name: streamlit-funplayer
Version: 0.1.29
Summary: Streamlit component for synchronized media and haptic playback using funscripts and Buttplug.io compatible devices
Author-email: Baptiste Ferrand <bferrand.math@gmail.com>
Maintainer-email: Baptiste Ferrand <bferrand.math@gmail.com>
License: MIT
Project-URL: Homepage, https://github.com/B4PT0R/streamlit-funplayer
Project-URL: Repository, https://github.com/B4PT0R/streamlit-funplayer
Project-URL: Bug Tracker, https://github.com/B4PT0R/streamlit-funplayer/issues
Project-URL: Documentation, https://github.com/B4PT0R/streamlit-funplayer#readme
Project-URL: Changelog, https://github.com/B4PT0R/streamlit-funplayer/releases
Keywords: streamlit,component,media-player,haptic-feedback,funscript,buttplug,adult-tech,interactive-media,vr,react
Classifier: Development Status :: 3 - Alpha
Classifier: Intended Audience :: Developers
Classifier: License :: OSI Approved :: MIT License
Classifier: Programming Language :: Python :: 3
Classifier: Programming Language :: Python :: 3.9
Classifier: Programming Language :: Python :: 3.10
Classifier: Programming Language :: Python :: 3.11
Classifier: Programming Language :: Python :: 3.12
Classifier: Programming Language :: JavaScript
Classifier: Topic :: Multimedia :: Video :: Display
Classifier: Topic :: Multimedia :: Sound/Audio :: Players
Classifier: Topic :: Scientific/Engineering :: Human Machine Interfaces
Classifier: Environment :: Web Environment
Classifier: Operating System :: OS Independent
Requires-Python: >=3.9
License-File: LICENSE
Requires-Dist: streamlit>=1.45.0
Provides-Extra: dev
Requires-Dist: pytest>=7.0.0; extra == "dev"
Requires-Dist: pytest-asyncio>=0.21.0; extra == "dev"
Requires-Dist: playwright>=1.40.0; extra == "dev"
Requires-Dist: black>=23.0.0; extra == "dev"
Requires-Dist: isort>=5.12.0; extra == "dev"
Requires-Dist: flake8>=6.0.0; extra == "dev"
Requires-Dist: mypy>=1.5.0; extra == "dev"
Requires-Dist: pre-commit>=3.0.0; extra == "dev"
Provides-Extra: test
Requires-Dist: pytest>=7.0.0; extra == "test"
Requires-Dist: pytest-asyncio>=0.21.0; extra == "test"
Requires-Dist: playwright>=1.40.0; extra == "test"
Provides-Extra: docs
Requires-Dist: sphinx>=7.0.0; extra == "docs"
Requires-Dist: sphinx-rtd-theme>=1.3.0; extra == "docs"
Requires-Dist: myst-parser>=2.0.0; extra == "docs"
Provides-Extra: examples
Requires-Dist: requests>=2.31.0; extra == "examples"
Requires-Dist: pillow>=10.0.0; extra == "examples"
Dynamic: license-file
